poetry_codeartifact_login_plugin/__init__.py
poetry_codeartifact_login_plugin/plugin.py
poetry_codeartifact_login_plugin-1.0.0.dist-info/LICENSE
poetry_codeartifact_login_plugin-1.0.0.dist-info/METADATA
poetry_codeartifact_login_plugin-1.0.0.dist-info/WHEEL
poetry_codeartifact_login_plugin-1.0.0.dist-info/entry_points.txt
poetry_codeartifact_login_plugin-1.0.0.dist-info/RECORD
