Metadata-Version: 2.1
Name: poetry-codeartifact-login-plugin
Version: 1.0.0
Summary: Poetry plugin to login to AWS CodeArtifact
Home-page: https://github.com/kc9ddi/poetry-codeartifact-login-plugin
License: MIT
Author: Patrick McDonnell
Author-email: kc9ddi@gmail.com
Requires-Python: >=3.8,<4.0
Classifier: License :: OSI Approved :: MIT License
Classifier: Programming Language :: Python :: 3
Classifier: Programming Language :: Python :: 3.8
Classifier: Programming Language :: Python :: 3.9
Classifier: Programming Language :: Python :: 3.10
Classifier: Programming Language :: Python :: 3.11
Classifier: Programming Language :: Python :: 3.12
Requires-Dist: poetry (>=1.2,<2.0)
Project-URL: Repository, https://github.com/kc9ddi/poetry-codeartifact-login-plugin
